{
	"configurations" : 
	[
		{
			"directories" : 
			[
				{
					"build" : ".",
					"hasInstallRule" : true,
					"jsonFile" : "directory-.-RelWithDebInfo-ce39da1d658fcc3580a9.json",
					"minimumCMakeVersion" : 
					{
						"string" : "3.12"
					},
					"projectIndex" : 0,
					"source" : ".",
					"targetIndexes" : 
					[
						0,
						1,
						2,
						3,
						4
					]
				}
			],
			"name" : "RelWithDebInfo",
			"projects" : 
			[
				{
					"directoryIndexes" : 
					[
						0
					],
					"name" : "hik_camera_driver",
					"targetIndexes" : 
					[
						0,
						1,
						2,
						3,
						4
					]
				}
			],
			"targets" : 
			[
				{
					"directoryIndex" : 0,
					"id" : "fps_monitor_node::@6890427a1f51a3e7e1df",
					"jsonFile" : "target-fps_monitor_node-RelWithDebInfo-9b56cb971f8d311208e4.json",
					"name" : "fps_monitor_node",
					"projectIndex" : 0
				},
				{
					"directoryIndex" : 0,
					"id" : "hik_camera_driver_uninstall::@6890427a1f51a3e7e1df",
					"jsonFile" : "target-hik_camera_driver_uninstall-RelWithDebInfo-bb2a9d6bef8e843d321d.json",
					"name" : "hik_camera_driver_uninstall",
					"projectIndex" : 0
				},
				{
					"directoryIndex" : 0,
					"id" : "hik_camera_node::@6890427a1f51a3e7e1df",
					"jsonFile" : "target-hik_camera_node-RelWithDebInfo-aa662be8f2df16f60cdd.json",
					"name" : "hik_camera_node",
					"projectIndex" : 0
				},
				{
					"directoryIndex" : 0,
					"id" : "param_info_node::@6890427a1f51a3e7e1df",
					"jsonFile" : "target-param_info_node-RelWithDebInfo-272299f353854058e7c5.json",
					"name" : "param_info_node",
					"projectIndex" : 0
				},
				{
					"directoryIndex" : 0,
					"id" : "uninstall::@6890427a1f51a3e7e1df",
					"jsonFile" : "target-uninstall-RelWithDebInfo-c9616bda11afc039938c.json",
					"name" : "uninstall",
					"projectIndex" : 0
				}
			]
		}
	],
	"kind" : "codemodel",
	"paths" : 
	{
		"build" : "/home/fin/Code/RoboMaster/Task4/build/hik_camera_driver",
		"source" : "/home/fin/Code/RoboMaster/Task4/hik_camera_driver"
	},
	"version" : 
	{
		"major" : 2,
		"minor" : 3
	}
}
